kudu/__init__.py
kudu/__main__.py
kudu/api.py
kudu/config.py
kudu/defaults.py
kudu/mkztemp.py
kudu/types.py
kudu/commands/__init__.py
kudu/commands/create.py
kudu/commands/init.py
kudu/commands/link.py
kudu/commands/pull.py
kudu/commands/push.py
kudu/tests/__init__.py
kudu/tests/test_link.py
kudu/tests/test_pull.py
kudu/tests/test_push.py
kudu-0.19.dist-info/licenses/LICENSE
kudu-0.19.dist-info/METADATA
kudu-0.19.dist-info/WHEEL
kudu-0.19.dist-info/entry_points.txt
kudu-0.19.dist-info/top_level.txt
kudu-0.19.dist-info/RECORD
